GandalfAPI/__init__.py
GandalfAPI/main.py
GandalfAPI/utils.py
GandalfAPI-1.0.0.dist-info/METADATA
GandalfAPI-1.0.0.dist-info/WHEEL
GandalfAPI-1.0.0.dist-info/top_level.txt
GandalfAPI-1.0.0.dist-info/RECORD
