Metadata-Version: 2.1
Name: GandalfAPI
Version: 1.0.0
Summary: A Python SDK for accessing The Lord of the Rings movie API
Author: Aleem Saleem
Author-email: mraleemsaleem@gmail.com
Keywords: lord-of-the-rings movie api sdk
Classifier: Development Status :: 4 - Beta
Classifier: Intended Audience :: Developers
Classifier: License :: OSI Approved :: MIT License
Classifier: Programming Language :: Python :: 3
Classifier: Programming Language :: Python :: 3.6
Classifier: Programming Language :: Python :: 3.7
Classifier: Programming Language :: Python :: 3.8
Classifier: Programming Language :: Python :: 3.9
Requires-Dist: requests (>=2.25.1)
